{
    "forge_marker": 1,
    "defaults": {
        "textures": {
            "top": "watergenerators:blocks/machine/top/darksteel",
            "side": "watergenerators:blocks/machine/side/darksteel"
        },
        "model": "watergenerators:generator_fluid"
    },
    "variants": {
        "normal": [
            {}
        ],
        "facing": {
            "north": {
                "y": 0
            },
            "south": {
                "y": 180
            },
            "west": {
                "y": 270
            },
            "east": {
                "y": 90
            }
        },
        "inventory": {
            "transform": "forge:default-block"
        }
    }
}